{
  "openapi": "3.0.1",
  "info": {
    "title": "TaskManager API",
    "version": "v1"
  },
  "paths": {
    "/api/Attachment": {
      "get": {
        "tags": [
          "Attachment"
        ],
        "parameters": [
          {
            "name": "FileName",
            "in": "query",
            "schema": {
              "type": "string"
            }
          },
          {
            "name": "ContentType",
            "in": "query",
            "schema": {
              "type": "string"
            }
          },
          {
            "name": "TaskItemId",
            "in": "query",
            "schema": {
              "type": "integer",
              "format": "int64"
            }
          },
          {
            "name": "UploadedByUserId",
            "in": "query",
            "schema": {
              "type": "string"
            }
          },
          {
            "name": "CreatedAt",
            "in": "query",
            "schema": {
              "type": "string",
              "format": "date-time"
            }
          },
          {
            "name": "Sorts",
            "in": "query",
            "schema": {
              "type": "array",
              "items": {
                "$ref": "#/components/schemas/AttachmentSortingFieldsSortOption"
              }
            }
          },
          {
            "name": "Search",
            "in": "query",
            "schema": {
              "type": "string"
            }
          },
          {
            "name": "Page",
            "in": "query",
            "schema": {
              "maximum": 2147483647,
              "minimum": 1,
              "type": "integer",
              "format": "int32"
            }
          },
          {
            "name": "PageSize",
            "in": "query",
            "schema": {
              "maximum": 100,
              "minimum": 1,
              "type": "integer",
              "format": "int32"
            }
          }
        ],
        "responses": {
          "200": {
            "description": "Success"
          }
        }
      },
      "post": {
        "tags": [
          "Attachment"
        ],
        "requestBody": {
          "content": {
            "application/json": {
              "schema": {
                "$ref": "#/components/schemas/AttachmentCreateDto"
              }
            },
            "text/json": {
              "schema": {
                "$ref": "#/components/schemas/AttachmentCreateDto"
              }
            },
            "application/*+json": {
              "schema": {
                "$ref": "#/components/schemas/AttachmentCreateDto"
              }
            }
          }
        },
        "responses": {
          "200": {
            "description": "Success"
          }
        }
      }
    },
    "/api/Attachment/{id}": {
      "delete": {
        "tags": [
          "Attachment"
        ],
        "parameters": [
          {
            "name": "id",
            "in": "path",
            "required": true,
            "schema": {
              "type": "integer",
              "format": "int64"
            }
          }
        ],
        "responses": {
          "200": {
            "description": "Success"
          }
        }
      }
    },
    "/api/AuditLog": {
      "get": {
        "tags": [
          "AuditLog"
        ],
        "parameters": [
          {
            "name": "Action",
            "in": "query",
            "schema": {
              "type": "string"
            }
          },
          {
            "name": "EntityName",
            "in": "query",
            "schema": {
              "type": "string"
            }
          },
          {
            "name": "EntityId",
            "in": "query",
            "schema": {
              "type": "string"
            }
          },
          {
            "name": "UserId",
            "in": "query",
            "schema": {
              "type": "string"
            }
          },
          {
            "name": "CreatedAt",
            "in": "query",
            "schema": {
              "type": "string",
              "format": "date-time"
            }
          },
          {
            "name": "Sorts",
            "in": "query",
            "schema": {
              "type": "array",
              "items": {
                "$ref": "#/components/schemas/AuditLogSortingFieldsSortOption"
              }
            }
          },
          {
            "name": "Search",
            "in": "query",
            "schema": {
              "type": "string"
            }
          },
          {
            "name": "Page",
            "in": "query",
            "schema": {
              "maximum": 2147483647,
              "minimum": 1,
              "type": "integer",
              "format": "int32"
            }
          },
          {
            "name": "PageSize",
            "in": "query",
            "schema": {
              "maximum": 100,
              "minimum": 1,
              "type": "integer",
              "format": "int32"
            }
          }
        ],
        "responses": {
          "200": {
            "description": "Success"
          }
        }
      }
    },
    "/api/Auth/Register": {
      "post": {
        "tags": [
          "Auth"
        ],
        "requestBody": {
          "content": {
            "application/json": {
              "schema": {
                "$ref": "#/components/schemas/RegisterDto"
              }
            },
            "text/json": {
              "schema": {
                "$ref": "#/components/schemas/RegisterDto"
              }
            },
            "application/*+json": {
              "schema": {
                "$ref": "#/components/schemas/RegisterDto"
              }
            }
          }
        },
        "responses": {
          "200": {
            "description": "Success"
          }
        }
      }
    },
    "/api/Auth/Login": {
      "post": {
        "tags": [
          "Auth"
        ],
        "requestBody": {
          "content": {
            "application/json": {
              "schema": {
                "$ref": "#/components/schemas/LoginDto"
              }
            },
            "text/json": {
              "schema": {
                "$ref": "#/components/schemas/LoginDto"
              }
            },
            "application/*+json": {
              "schema": {
                "$ref": "#/components/schemas/LoginDto"
              }
            }
          }
        },
        "responses": {
          "200": {
            "description": "Success"
          }
        }
      }
    },
    "/api/Comment": {
      "get": {
        "tags": [
          "Comment"
        ],
        "parameters": [
          {
            "name": "Content",
            "in": "query",
            "schema": {
              "type": "string"
            }
          },
          {
            "name": "DateFrom",
            "in": "query",
            "schema": {
              "type": "string",
              "format": "date-time"
            }
          },
          {
            "name": "DateTo",
            "in": "query",
            "schema": {
              "type": "string",
              "format": "date-time"
            }
          },
          {
            "name": "TaskId",
            "in": "query",
            "schema": {
              "type": "integer",
              "format": "int64"
            }
          },
          {
            "name": "UserId",
            "in": "query",
            "schema": {
              "type": "string"
            }
          },
          {
            "name": "Sorts",
            "in": "query",
            "schema": {
              "type": "array",
              "items": {
                "$ref": "#/components/schemas/CommentSortingFieldsSortOption"
              }
            }
          },
          {
            "name": "Search",
            "in": "query",
            "schema": {
              "type": "string"
            }
          },
          {
            "name": "Page",
            "in": "query",
            "schema": {
              "maximum": 2147483647,
              "minimum": 1,
              "type": "integer",
              "format": "int32"
            }
          },
          {
            "name": "PageSize",
            "in": "query",
            "schema": {
              "maximum": 100,
              "minimum": 1,
              "type": "integer",
              "format": "int32"
            }
          }
        ],
        "responses": {
          "200": {
            "description": "Success"
          }
        }
      }
    },
    "/api/Comment/tasks/{taskId}/comments": {
      "get": {
        "tags": [
          "Comment"
        ],
        "parameters": [
          {
            "name": "taskId",
            "in": "path",
            "required": true,
            "schema": {
              "type": "integer",
              "format": "int64"
            }
          }
        ],
        "responses": {
          "200": {
            "description": "Success"
          }
        }
      },
      "post": {
        "tags": [
          "Comment"
        ],
        "parameters": [
          {
            "name": "taskId",
            "in": "path",
            "required": true,
            "schema": {
              "type": "integer",
              "format": "int64"
            }
          }
        ],
        "requestBody": {
          "content": {
            "application/json": {
              "schema": {
                "$ref": "#/components/schemas/CommentCreateDto"
              }
            },
            "text/json": {
              "schema": {
                "$ref": "#/components/schemas/CommentCreateDto"
              }
            },
            "application/*+json": {
              "schema": {
                "$ref": "#/components/schemas/CommentCreateDto"
              }
            }
          }
        },
        "responses": {
          "200": {
            "description": "Success"
          }
        }
      }
    },
    "/api/Comment/{id}": {
      "put": {
        "tags": [
          "Comment"
        ],
        "parameters": [
          {
            "name": "id",
            "in": "path",
            "required": true,
            "schema": {
              "type": "integer",
              "format": "int64"
            }
          },
          {
            "name": "canManageAny",
            "in": "query",
            "schema": {
              "type": "boolean"
            }
          }
        ],
        "requestBody": {
          "content": {
            "application/json": {
              "schema": {
                "$ref": "#/components/schemas/CommentUpdateDto"
              }
            },
            "text/json": {
              "schema": {
                "$ref": "#/components/schemas/CommentUpdateDto"
              }
            },
            "application/*+json": {
              "schema": {
                "$ref": "#/components/schemas/CommentUpdateDto"
              }
            }
          }
        },
        "responses": {
          "200": {
            "description": "Success"
          }
        }
      },
      "delete": {
        "tags": [
          "Comment"
        ],
        "parameters": [
          {
            "name": "id",
            "in": "path",
            "required": true,
            "schema": {
              "type": "integer",
              "format": "int64"
            }
          }
        ],
        "responses": {
          "200": {
            "description": "Success"
          }
        }
      }
    },
    "/api/Notification": {
      "get": {
        "tags": [
          "Notification"
        ],
        "parameters": [
          {
            "name": "Title",
            "in": "query",
            "schema": {
              "type": "string"
            }
          },
          {
            "name": "IsRead",
            "in": "query",
            "schema": {
              "type": "boolean"
            }
          },
          {
            "name": "UserId",
            "in": "query",
            "schema": {
              "type": "string"
            }
          },
          {
            "name": "CreatedAt",
            "in": "query",
            "schema": {
              "type": "string",
              "format": "date-time"
            }
          },
          {
            "name": "Sorts",
            "in": "query",
            "schema": {
              "type": "array",
              "items": {
                "$ref": "#/components/schemas/NotificationSortingFieldsSortOption"
              }
            }
          },
          {
            "name": "Search",
            "in": "query",
            "schema": {
              "type": "string"
            }
          },
          {
            "name": "Page",
            "in": "query",
            "schema": {
              "maximum": 2147483647,
              "minimum": 1,
              "type": "integer",
              "format": "int32"
            }
          },
          {
            "name": "PageSize",
            "in": "query",
            "schema": {
              "maximum": 100,
              "minimum": 1,
              "type": "integer",
              "format": "int32"
            }
          }
        ],
        "responses": {
          "200": {
            "description": "Success"
          }
        }
      }
    },
    "/api/Notification/{id}/read": {
      "patch": {
        "tags": [
          "Notification"
        ],
        "parameters": [
          {
            "name": "id",
            "in": "path",
            "required": true,
            "schema": {
              "type": "integer",
              "format": "int64"
            }
          }
        ],
        "responses": {
          "200": {
            "description": "Success"
          }
        }
      }
    },
    "/api/Notification/{id}": {
      "delete": {
        "tags": [
          "Notification"
        ],
        "parameters": [
          {
            "name": "id",
            "in": "path",
            "required": true,
            "schema": {
              "type": "integer",
              "format": "int64"
            }
          }
        ],
        "responses": {
          "200": {
            "description": "Success"
          }
        }
      }
    },
    "/api/Project": {
      "get": {
        "tags": [
          "Project"
        ],
        "parameters": [
          {
            "name": "Name",
            "in": "query",
            "schema": {
              "type": "string"
            }
          },
          {
            "name": "Description",
            "in": "query",
            "schema": {
              "type": "string"
            }
          },
          {
            "name": "IsArchived",
            "in": "query",
            "schema": {
              "type": "boolean"
            }
          },
          {
            "name": "TeamId",
            "in": "query",
            "schema": {
              "type": "integer",
              "format": "int64"
            }
          },
          {
            "name": "CreatedByUserId",
            "in": "query",
            "schema": {
              "type": "string"
            }
          },
          {
            "name": "StartDate",
            "in": "query",
            "schema": {
              "type": "string",
              "format": "date-time"
            }
          },
          {
            "name": "EndDate",
            "in": "query",
            "schema": {
              "type": "string",
              "format": "date-time"
            }
          },
          {
            "name": "CreatedAt",
            "in": "query",
            "schema": {
              "type": "string",
              "format": "date-time"
            }
          },
          {
            "name": "Sorts",
            "in": "query",
            "schema": {
              "type": "array",
              "items": {
                "$ref": "#/components/schemas/ProjectSortingFieldsSortOption"
              }
            }
          },
          {
            "name": "Search",
            "in": "query",
            "schema": {
              "type": "string"
            }
          },
          {
            "name": "Page",
            "in": "query",
            "schema": {
              "maximum": 2147483647,
              "minimum": 1,
              "type": "integer",
              "format": "int32"
            }
          },
          {
            "name": "PageSize",
            "in": "query",
            "schema": {
              "maximum": 100,
              "minimum": 1,
              "type": "integer",
              "format": "int32"
            }
          }
        ],
        "responses": {
          "200": {
            "description": "Success"
          }
        }
      },
      "post": {
        "tags": [
          "Project"
        ],
        "requestBody": {
          "content": {
            "application/json": {
              "schema": {
                "$ref": "#/components/schemas/ProjectCreateDto"
              }
            },
            "text/json": {
              "schema": {
                "$ref": "#/components/schemas/ProjectCreateDto"
              }
            },
            "application/*+json": {
              "schema": {
                "$ref": "#/components/schemas/ProjectCreateDto"
              }
            }
          }
        },
        "responses": {
          "200": {
            "description": "Success"
          }
        }
      }
    },
    "/api/Project/{id}": {
      "get": {
        "tags": [
          "Project"
        ],
        "parameters": [
          {
            "name": "id",
            "in": "path",
            "required": true,
            "schema": {
              "type": "integer",
              "format": "int64"
            }
          }
        ],
        "responses": {
          "200": {
            "description": "Success"
          }
        }
      },
      "put": {
        "tags": [
          "Project"
        ],
        "parameters": [
          {
            "name": "id",
            "in": "path",
            "required": true,
            "schema": {
              "type": "integer",
              "format": "int64"
            }
          }
        ],
        "requestBody": {
          "content": {
            "application/json": {
              "schema": {
                "$ref": "#/components/schemas/ProjectUpdateDto"
              }
            },
            "text/json": {
              "schema": {
                "$ref": "#/components/schemas/ProjectUpdateDto"
              }
            },
            "application/*+json": {
              "schema": {
                "$ref": "#/components/schemas/ProjectUpdateDto"
              }
            }
          }
        },
        "responses": {
          "200": {
            "description": "Success"
          }
        }
      },
      "delete": {
        "tags": [
          "Project"
        ],
        "parameters": [
          {
            "name": "id",
            "in": "path",
            "required": true,
            "schema": {
              "type": "integer",
              "format": "int64"
            }
          }
        ],
        "responses": {
          "200": {
            "description": "Success"
          }
        }
      }
    },
    "/api/Role": {
      "get": {
        "tags": [
          "Role"
        ],
        "parameters": [
          {
            "name": "Name",
            "in": "query",
            "schema": {
              "type": "string"
            }
          },
          {
            "name": "Description",
            "in": "query",
            "schema": {
              "type": "string"
            }
          },
          {
            "name": "Sorts",
            "in": "query",
            "schema": {
              "type": "array",
              "items": {
                "$ref": "#/components/schemas/RoleSortingFieldsSortOption"
              }
            }
          },
          {
            "name": "Search",
            "in": "query",
            "schema": {
              "type": "string"
            }
          },
          {
            "name": "Page",
            "in": "query",
            "schema": {
              "maximum": 2147483647,
              "minimum": 1,
              "type": "integer",
              "format": "int32"
            }
          },
          {
            "name": "PageSize",
            "in": "query",
            "schema": {
              "maximum": 100,
              "minimum": 1,
              "type": "integer",
              "format": "int32"
            }
          }
        ],
        "responses": {
          "200": {
            "description": "Success"
          }
        }
      },
      "post": {
        "tags": [
          "Role"
        ],
        "requestBody": {
          "content": {
            "application/json": {
              "schema": {
                "$ref": "#/components/schemas/RoleCreateAndUpdateDto"
              }
            },
            "text/json": {
              "schema": {
                "$ref": "#/components/schemas/RoleCreateAndUpdateDto"
              }
            },
            "application/*+json": {
              "schema": {
                "$ref": "#/components/schemas/RoleCreateAndUpdateDto"
              }
            }
          }
        },
        "responses": {
          "200": {
            "description": "Success"
          }
        }
      }
    },
    "/api/Role/{id}": {
      "get": {
        "tags": [
          "Role"
        ],
        "parameters": [
          {
            "name": "id",
            "in": "path",
            "required": true,
            "schema": {
              "type": "string"
            }
          }
        ],
        "responses": {
          "200": {
            "description": "Success"
          }
        }
      },
      "put": {
        "tags": [
          "Role"
        ],
        "parameters": [
          {
            "name": "id",
            "in": "path",
            "required": true,
            "schema": {
              "type": "string"
            }
          }
        ],
        "requestBody": {
          "content": {
            "application/json": {
              "schema": {
                "$ref": "#/components/schemas/RoleCreateAndUpdateDto"
              }
            },
            "text/json": {
              "schema": {
                "$ref": "#/components/schemas/RoleCreateAndUpdateDto"
              }
            },
            "application/*+json": {
              "schema": {
                "$ref": "#/components/schemas/RoleCreateAndUpdateDto"
              }
            }
          }
        },
        "responses": {
          "200": {
            "description": "Success"
          }
        }
      },
      "delete": {
        "tags": [
          "Role"
        ],
        "parameters": [
          {
            "name": "id",
            "in": "path",
            "required": true,
            "schema": {
              "type": "string"
            }
          }
        ],
        "responses": {
          "200": {
            "description": "Success"
          }
        }
      }
    },
    "/api/Task": {
      "get": {
        "tags": [
          "Task"
        ],
        "parameters": [
          {
            "name": "Title",
            "in": "query",
            "schema": {
              "type": "string"
            }
          },
          {
            "name": "Description",
            "in": "query",
            "schema": {
              "type": "string"
            }
          },
          {
            "name": "Status",
            "in": "query",
            "schema": {
              "$ref": "#/components/schemas/TaskItemStatus"
            }
          },
          {
            "name": "Priority",
            "in": "query",
            "schema": {
              "$ref": "#/components/schemas/TaskPriority"
            }
          },
          {
            "name": "ProjectId",
            "in": "query",
            "schema": {
              "type": "integer",
              "format": "int64"
            }
          },
          {
            "name": "CreatedByUserId",
            "in": "query",
            "schema": {
              "type": "string"
            }
          },
          {
            "name": "DueDate",
            "in": "query",
            "schema": {
              "type": "string",
              "format": "date-time"
            }
          },
          {
            "name": "CompletedAt",
            "in": "query",
            "schema": {
              "type": "string",
              "format": "date-time"
            }
          },
          {
            "name": "CreatedAt",
            "in": "query",
            "schema": {
              "type": "string",
              "format": "date-time"
            }
          },
          {
            "name": "Sorts",
            "in": "query",
            "schema": {
              "type": "array",
              "items": {
                "$ref": "#/components/schemas/TaskSortingFieldsSortOption"
              }
            }
          },
          {
            "name": "Search",
            "in": "query",
            "schema": {
              "type": "string"
            }
          },
          {
            "name": "Page",
            "in": "query",
            "schema": {
              "maximum": 2147483647,
              "minimum": 1,
              "type": "integer",
              "format": "int32"
            }
          },
          {
            "name": "PageSize",
            "in": "query",
            "schema": {
              "maximum": 100,
              "minimum": 1,
              "type": "integer",
              "format": "int32"
            }
          }
        ],
        "responses": {
          "200": {
            "description": "Success"
          }
        }
      },
      "post": {
        "tags": [
          "Task"
        ],
        "requestBody": {
          "content": {
            "application/json": {
              "schema": {
                "$ref": "#/components/schemas/TaskCreateDto"
              }
            },
            "text/json": {
              "schema": {
                "$ref": "#/components/schemas/TaskCreateDto"
              }
            },
            "application/*+json": {
              "schema": {
                "$ref": "#/components/schemas/TaskCreateDto"
              }
            }
          }
        },
        "responses": {
          "200": {
            "description": "Success"
          }
        }
      }
    },
    "/api/Task/{id}": {
      "get": {
        "tags": [
          "Task"
        ],
        "parameters": [
          {
            "name": "id",
            "in": "path",
            "required": true,
            "schema": {
              "type": "integer",
              "format": "int64"
            }
          }
        ],
        "responses": {
          "200": {
            "description": "Success"
          }
        }
      },
      "put": {
        "tags": [
          "Task"
        ],
        "parameters": [
          {
            "name": "id",
            "in": "path",
            "required": true,
            "schema": {
              "type": "integer",
              "format": "int64"
            }
          }
        ],
        "requestBody": {
          "content": {
            "application/json": {
              "schema": {
                "$ref": "#/components/schemas/TaskUpdateDto"
              }
            },
            "text/json": {
              "schema": {
                "$ref": "#/components/schemas/TaskUpdateDto"
              }
            },
            "application/*+json": {
              "schema": {
                "$ref": "#/components/schemas/TaskUpdateDto"
              }
            }
          }
        },
        "responses": {
          "200": {
            "description": "Success"
          }
        }
      },
      "delete": {
        "tags": [
          "Task"
        ],
        "parameters": [
          {
            "name": "id",
            "in": "path",
            "required": true,
            "schema": {
              "type": "integer",
              "format": "int64"
            }
          }
        ],
        "responses": {
          "200": {
            "description": "Success"
          }
        }
      }
    },
    "/api/Task/{id}/assign": {
      "post": {
        "tags": [
          "Task"
        ],
        "parameters": [
          {
            "name": "id",
            "in": "path",
            "required": true,
            "schema": {
              "type": "integer",
              "format": "int64"
            }
          }
        ],
        "requestBody": {
          "content": {
            "application/json": {
              "schema": {
                "$ref": "#/components/schemas/AssignTaskDto"
              }
            },
            "text/json": {
              "schema": {
                "$ref": "#/components/schemas/AssignTaskDto"
              }
            },
            "application/*+json": {
              "schema": {
                "$ref": "#/components/schemas/AssignTaskDto"
              }
            }
          }
        },
        "responses": {
          "200": {
            "description": "Success"
          }
        }
      }
    },
    "/api/Task/{id}/assign/{userId}": {
      "delete": {
        "tags": [
          "Task"
        ],
        "parameters": [
          {
            "name": "id",
            "in": "path",
            "required": true,
            "schema": {
              "type": "integer",
              "format": "int64"
            }
          },
          {
            "name": "userId",
            "in": "path",
            "required": true,
            "schema": {
              "type": "string"
            }
          }
        ],
        "responses": {
          "200": {
            "description": "Success"
          }
        }
      }
    },
    "/api/Task/{id}/status": {
      "patch": {
        "tags": [
          "Task"
        ],
        "parameters": [
          {
            "name": "id",
            "in": "path",
            "required": true,
            "schema": {
              "type": "integer",
              "format": "int64"
            }
          }
        ],
        "requestBody": {
          "content": {
            "application/json": {
              "schema": {
                "$ref": "#/components/schemas/ChangeTaskStatusDto"
              }
            },
            "text/json": {
              "schema": {
                "$ref": "#/components/schemas/ChangeTaskStatusDto"
              }
            },
            "application/*+json": {
              "schema": {
                "$ref": "#/components/schemas/ChangeTaskStatusDto"
              }
            }
          }
        },
        "responses": {
          "200": {
            "description": "Success"
          }
        }
      }
    },
    "/api/Task/{id}/priority": {
      "patch": {
        "tags": [
          "Task"
        ],
        "parameters": [
          {
            "name": "id",
            "in": "path",
            "required": true,
            "schema": {
              "type": "integer",
              "format": "int64"
            }
          }
        ],
        "requestBody": {
          "content": {
            "application/json": {
              "schema": {
                "$ref": "#/components/schemas/ChangeTaskPriorityDto"
              }
            },
            "text/json": {
              "schema": {
                "$ref": "#/components/schemas/ChangeTaskPriorityDto"
              }
            },
            "application/*+json": {
              "schema": {
                "$ref": "#/components/schemas/ChangeTaskPriorityDto"
              }
            }
          }
        },
        "responses": {
          "200": {
            "description": "Success"
          }
        }
      }
    },
    "/api/TaskAssignment": {
      "get": {
        "tags": [
          "TaskAssignment"
        ],
        "parameters": [
          {
            "name": "TaskItemId",
            "in": "query",
            "schema": {
              "type": "integer",
              "format": "int64"
            }
          },
          {
            "name": "UserId",
            "in": "query",
            "schema": {
              "type": "string"
            }
          },
          {
            "name": "AssignedByUserId",
            "in": "query",
            "schema": {
              "type": "string"
            }
          },
          {
            "name": "AssignedAt",
            "in": "query",
            "schema": {
              "type": "string",
              "format": "date-time"
            }
          },
          {
            "name": "Sorts",
            "in": "query",
            "schema": {
              "type": "array",
              "items": {
                "$ref": "#/components/schemas/TaskAssignmentSortingFieldsSortOption"
              }
            }
          },
          {
            "name": "Search",
            "in": "query",
            "schema": {
              "type": "string"
            }
          },
          {
            "name": "Page",
            "in": "query",
            "schema": {
              "maximum": 2147483647,
              "minimum": 1,
              "type": "integer",
              "format": "int32"
            }
          },
          {
            "name": "PageSize",
            "in": "query",
            "schema": {
              "maximum": 100,
              "minimum": 1,
              "type": "integer",
              "format": "int32"
            }
          }
        ],
        "responses": {
          "200": {
            "description": "Success"
          }
        }
      }
    },
    "/api/TaskStatusHistory": {
      "get": {
        "tags": [
          "TaskStatusHistory"
        ],
        "parameters": [
          {
            "name": "TaskItemId",
            "in": "query",
            "schema": {
              "type": "integer",
              "format": "int64"
            }
          },
          {
            "name": "OldStatus",
            "in": "query",
            "schema": {
              "$ref": "#/components/schemas/TaskStatus"
            }
          },
          {
            "name": "NewStatus",
            "in": "query",
            "schema": {
              "$ref": "#/components/schemas/TaskStatus"
            }
          },
          {
            "name": "ChangedByUserId",
            "in": "query",
            "schema": {
              "type": "string"
            }
          },
          {
            "name": "ChangedAt",
            "in": "query",
            "schema": {
              "type": "string",
              "format": "date-time"
            }
          },
          {
            "name": "Sorts",
            "in": "query",
            "schema": {
              "type": "array",
              "items": {
                "$ref": "#/components/schemas/TaskStatusHistorySortingFieldsSortOption"
              }
            }
          },
          {
            "name": "Search",
            "in": "query",
            "schema": {
              "type": "string"
            }
          },
          {
            "name": "Page",
            "in": "query",
            "schema": {
              "maximum": 2147483647,
              "minimum": 1,
              "type": "integer",
              "format": "int32"
            }
          },
          {
            "name": "PageSize",
            "in": "query",
            "schema": {
              "maximum": 100,
              "minimum": 1,
              "type": "integer",
              "format": "int32"
            }
          }
        ],
        "responses": {
          "200": {
            "description": "Success"
          }
        }
      }
    },
    "/api/Team": {
      "get": {
        "tags": [
          "Team"
        ],
        "parameters": [
          {
            "name": "Name",
            "in": "query",
            "schema": {
              "type": "string"
            }
          },
          {
            "name": "Description",
            "in": "query",
            "schema": {
              "type": "string"
            }
          },
          {
            "name": "ManagerId",
            "in": "query",
            "schema": {
              "type": "string"
            }
          },
          {
            "name": "CreatedAt",
            "in": "query",
            "schema": {
              "type": "string",
              "format": "date-time"
            }
          },
          {
            "name": "Sorts",
            "in": "query",
            "schema": {
              "type": "array",
              "items": {
                "$ref": "#/components/schemas/TeamSortingFieldsSortOption"
              }
            }
          },
          {
            "name": "Search",
            "in": "query",
            "schema": {
              "type": "string"
            }
          },
          {
            "name": "Page",
            "in": "query",
            "schema": {
              "maximum": 2147483647,
              "minimum": 1,
              "type": "integer",
              "format": "int32"
            }
          },
          {
            "name": "PageSize",
            "in": "query",
            "schema": {
              "maximum": 100,
              "minimum": 1,
              "type": "integer",
              "format": "int32"
            }
          }
        ],
        "responses": {
          "200": {
            "description": "Success"
          }
        }
      },
      "post": {
        "tags": [
          "Team"
        ],
        "requestBody": {
          "content": {
            "application/json": {
              "schema": {
                "$ref": "#/components/schemas/TeamCreateDto"
              }
            },
            "text/json": {
              "schema": {
                "$ref": "#/components/schemas/TeamCreateDto"
              }
            },
            "application/*+json": {
              "schema": {
                "$ref": "#/components/schemas/TeamCreateDto"
              }
            }
          }
        },
        "responses": {
          "200": {
            "description": "Success"
          }
        }
      }
    },
    "/api/Team/{id}": {
      "get": {
        "tags": [
          "Team"
        ],
        "parameters": [
          {
            "name": "id",
            "in": "path",
            "required": true,
            "schema": {
              "type": "integer",
              "format": "int64"
            }
          }
        ],
        "responses": {
          "200": {
            "description": "Success"
          }
        }
      },
      "put": {
        "tags": [
          "Team"
        ],
        "parameters": [
          {
            "name": "id",
            "in": "path",
            "required": true,
            "schema": {
              "type": "integer",
              "format": "int64"
            }
          }
        ],
        "requestBody": {
          "content": {
            "application/json": {
              "schema": {
                "$ref": "#/components/schemas/TeamUpdateDto"
              }
            },
            "text/json": {
              "schema": {
                "$ref": "#/components/schemas/TeamUpdateDto"
              }
            },
            "application/*+json": {
              "schema": {
                "$ref": "#/components/schemas/TeamUpdateDto"
              }
            }
          }
        },
        "responses": {
          "200": {
            "description": "Success"
          }
        }
      },
      "delete": {
        "tags": [
          "Team"
        ],
        "parameters": [
          {
            "name": "id",
            "in": "path",
            "required": true,
            "schema": {
              "type": "integer",
              "format": "int64"
            }
          }
        ],
        "responses": {
          "200": {
            "description": "Success"
          }
        }
      }
    },
    "/api/User": {
      "get": {
        "tags": [
          "User"
        ],
        "parameters": [
          {
            "name": "UserName",
            "in": "query",
            "schema": {
              "type": "string"
            }
          },
          {
            "name": "IsActive",
            "in": "query",
            "schema": {
              "type": "boolean"
            }
          },
          {
            "name": "TeamId",
            "in": "query",
            "schema": {
              "type": "integer",
              "format": "int64"
            }
          },
          {
            "name": "LastLoginAt",
            "in": "query",
            "schema": {
              "type": "string",
              "format": "date-time"
            }
          },
          {
            "name": "CreatedAt",
            "in": "query",
            "schema": {
              "type": "string",
              "format": "date-time"
            }
          },
          {
            "name": "Sorts",
            "in": "query",
            "schema": {
              "type": "array",
              "items": {
                "$ref": "#/components/schemas/UserSortingFieldsSortOption"
              }
            }
          },
          {
            "name": "Search",
            "in": "query",
            "schema": {
              "type": "string"
            }
          },
          {
            "name": "Page",
            "in": "query",
            "schema": {
              "maximum": 2147483647,
              "minimum": 1,
              "type": "integer",
              "format": "int32"
            }
          },
          {
            "name": "PageSize",
            "in": "query",
            "schema": {
              "maximum": 100,
              "minimum": 1,
              "type": "integer",
              "format": "int32"
            }
          }
        ],
        "responses": {
          "200": {
            "description": "Success"
          }
        }
      }
    },
    "/api/User/{id}": {
      "get": {
        "tags": [
          "User"
        ],
        "parameters": [
          {
            "name": "id",
            "in": "path",
            "required": true,
            "schema": {
              "type": "string"
            }
          }
        ],
        "responses": {
          "200": {
            "description": "Success"
          }
        }
      },
      "put": {
        "tags": [
          "User"
        ],
        "parameters": [
          {
            "name": "id",
            "in": "path",
            "required": true,
            "schema": {
              "type": "string"
            }
          }
        ],
        "requestBody": {
          "content": {
            "application/json": {
              "schema": {
                "$ref": "#/components/schemas/UserUpdateDto"
              }
            },
            "text/json": {
              "schema": {
                "$ref": "#/components/schemas/UserUpdateDto"
              }
            },
            "application/*+json": {
              "schema": {
                "$ref": "#/components/schemas/UserUpdateDto"
              }
            }
          }
        },
        "responses": {
          "200": {
            "description": "Success"
          }
        }
      },
      "delete": {
        "tags": [
          "User"
        ],
        "parameters": [
          {
            "name": "id",
            "in": "path",
            "required": true,
            "schema": {
              "type": "string"
            }
          }
        ],
        "responses": {
          "200": {
            "description": "Success"
          }
        }
      }
    },
    "/api/User/{id}/status": {
      "patch": {
        "tags": [
          "User"
        ],
        "parameters": [
          {
            "name": "id",
            "in": "path",
            "required": true,
            "schema": {
              "type": "string"
            }
          }
        ],
        "requestBody": {
          "content": {
            "application/json": {
              "schema": {
                "$ref": "#/components/schemas/UserStatusDto"
              }
            },
            "text/json": {
              "schema": {
                "$ref": "#/components/schemas/UserStatusDto"
              }
            },
            "application/*+json": {
              "schema": {
                "$ref": "#/components/schemas/UserStatusDto"
              }
            }
          }
        },
        "responses": {
          "200": {
            "description": "Success"
          }
        }
      }
    },
    "/api/User/{id}/roles": {
      "post": {
        "tags": [
          "User"
        ],
        "parameters": [
          {
            "name": "id",
            "in": "path",
            "required": true,
            "schema": {
              "type": "string"
            }
          }
        ],
        "requestBody": {
          "content": {
            "application/json": {
              "schema": {
                "$ref": "#/components/schemas/AssignRoleDto"
              }
            },
            "text/json": {
              "schema": {
                "$ref": "#/components/schemas/AssignRoleDto"
              }
            },
            "application/*+json": {
              "schema": {
                "$ref": "#/components/schemas/AssignRoleDto"
              }
            }
          }
        },
        "responses": {
          "200": {
            "description": "Success"
          }
        }
      }
    },
    "/api/User/{id}/roles/{roleName}": {
      "delete": {
        "tags": [
          "User"
        ],
        "parameters": [
          {
            "name": "id",
            "in": "path",
            "required": true,
            "schema": {
              "type": "string"
            }
          },
          {
            "name": "roleName",
            "in": "path",
            "required": true,
            "schema": {
              "type": "string"
            }
          }
        ],
        "responses": {
          "200": {
            "description": "Success"
          }
        }
      }
    }
  },
  "components": {
    "schemas": {
      "AssignRoleDto": {
        "type": "object",
        "properties": {
          "roleName": {
            "type": "string",
            "nullable": true
          },
          "userId": {
            "type": "string",
            "nullable": true
          }
        },
        "additionalProperties": false
      },
      "AssignTaskDto": {
        "type": "object",
        "properties": {
          "userId": {
            "type": "string",
            "nullable": true
          }
        },
        "additionalProperties": false
      },
      "AttachmentCreateDto": {
        "type": "object",
        "properties": {
          "taskItemId": {
            "type": "integer",
            "format": "int64"
          },
          "fileName": {
            "type": "string",
            "nullable": true
          },
          "storedFileName": {
            "type": "string",
            "nullable": true
          },
          "filePath": {
            "type": "string",
            "nullable": true
          },
          "contentType": {
            "type": "string",
            "nullable": true
          },
          "fileSize": {
            "type": "integer",
            "format": "int64"
          }
        },
        "additionalProperties": false
      },
      "AttachmentSortingFields": {
        "enum": [
          "Id",
          "FileName",
          "FileSize",
          "ContentType",
          "UploadedByUserId",
          "CreatedAt"
        ],
        "type": "string"
      },
      "AttachmentSortingFieldsSortOption": {
        "type": "object",
        "properties": {
          "field": {
            "$ref": "#/components/schemas/AttachmentSortingFields"
          },
          "direction": {
            "$ref": "#/components/schemas/SortDirection"
          }
        },
        "additionalProperties": false
      },
      "AuditLogSortingFields": {
        "enum": [
          "Id",
          "Action",
          "EntityName",
          "UserId",
          "CreatedAt"
        ],
        "type": "string"
      },
      "AuditLogSortingFieldsSortOption": {
        "type": "object",
        "properties": {
          "field": {
            "$ref": "#/components/schemas/AuditLogSortingFields"
          },
          "direction": {
            "$ref": "#/components/schemas/SortDirection"
          }
        },
        "additionalProperties": false
      },
      "ChangeTaskPriorityDto": {
        "type": "object",
        "properties": {
          "newPriority": {
            "$ref": "#/components/schemas/TaskPriority"
          }
        },
        "additionalProperties": false
      },
      "ChangeTaskStatusDto": {
        "type": "object",
        "properties": {
          "newStatus": {
            "$ref": "#/components/schemas/TaskItemStatus"
          }
        },
        "additionalProperties": false
      },
      "CommentCreateDto": {
        "type": "object",
        "properties": {
          "taskItemId": {
            "type": "integer",
            "format": "int64"
          },
          "content": {
            "type": "string",
            "nullable": true
          }
        },
        "additionalProperties": false
      },
      "CommentSortingFields": {
        "enum": [
          "Id",
          "Content",
          "CreatedAt",
          "TaskItemId",
          "UserId"
        ],
        "type": "string"
      },
      "CommentSortingFieldsSortOption": {
        "type": "object",
        "properties": {
          "field": {
            "$ref": "#/components/schemas/CommentSortingFields"
          },
          "direction": {
            "$ref": "#/components/schemas/SortDirection"
          }
        },
        "additionalProperties": false
      },
      "CommentUpdateDto": {
        "type": "object",
        "properties": {
          "content": {
            "type": "string",
            "nullable": true
          }
        },
        "additionalProperties": false
      },
      "LoginDto": {
        "type": "object",
        "properties": {
          "email": {
            "type": "string",
            "nullable": true
          },
          "password": {
            "type": "string",
            "nullable": true
          }
        },
        "additionalProperties": false
      },
      "NotificationSortingFields": {
        "enum": [
          "Id",
          "Title",
          "IsRead",
          "UserId",
          "CreatedAt"
        ],
        "type": "string"
      },
      "NotificationSortingFieldsSortOption": {
        "type": "object",
        "properties": {
          "field": {
            "$ref": "#/components/schemas/NotificationSortingFields"
          },
          "direction": {
            "$ref": "#/components/schemas/SortDirection"
          }
        },
        "additionalProperties": false
      },
      "ProjectCreateDto": {
        "type": "object",
        "properties": {
          "name": {
            "type": "string",
            "nullable": true
          },
          "description": {
            "type": "string",
            "nullable": true
          },
          "startDate": {
            "type": "string",
            "format": "date-time",
            "nullable": true
          },
          "endDate": {
            "type": "string",
            "format": "date-time",
            "nullable": true
          },
          "teamId": {
            "type": "integer",
            "format": "int64"
          }
        },
        "additionalProperties": false
      },
      "ProjectSortingFields": {
        "enum": [
          "Id",
          "Name",
          "IsArchived",
          "StartDate",
          "EndDate",
          "TeamId",
          "CreatedByUserId",
          "CreatedAt"
        ],
        "type": "string"
      },
      "ProjectSortingFieldsSortOption": {
        "type": "object",
        "properties": {
          "field": {
            "$ref": "#/components/schemas/ProjectSortingFields"
          },
          "direction": {
            "$ref": "#/components/schemas/SortDirection"
          }
        },
        "additionalProperties": false
      },
      "ProjectUpdateDto": {
        "type": "object",
        "properties": {
          "name": {
            "type": "string",
            "nullable": true
          },
          "description": {
            "type": "string",
            "nullable": true
          },
          "startDate": {
            "type": "string",
            "format": "date-time",
            "nullable": true
          },
          "endDate": {
            "type": "string",
            "format": "date-time",
            "nullable": true
          },
          "isArchived": {
            "type": "boolean"
          }
        },
        "additionalProperties": false
      },
      "RegisterDto": {
        "type": "object",
        "properties": {
          "userName": {
            "type": "string",
            "nullable": true
          },
          "email": {
            "type": "string",
            "nullable": true
          },
          "password": {
            "type": "string",
            "nullable": true
          }
        },
        "additionalProperties": false
      },
      "RoleCreateAndUpdateDto": {
        "type": "object",
        "properties": {
          "name": {
            "type": "string",
            "nullable": true
          },
          "description": {
            "type": "string",
            "nullable": true
          }
        },
        "additionalProperties": false
      },
      "RoleSortingFields": {
        "enum": [
          "Id",
          "Name",
          "Description"
        ],
        "type": "string"
      },
      "RoleSortingFieldsSortOption": {
        "type": "object",
        "properties": {
          "field": {
            "$ref": "#/components/schemas/RoleSortingFields"
          },
          "direction": {
            "$ref": "#/components/schemas/SortDirection"
          }
        },
        "additionalProperties": false
      },
      "SortDirection": {
        "enum": [
          "Ascending",
          "Descending"
        ],
        "type": "string"
      },
      "TaskAssignmentSortingFields": {
        "enum": [
          "Id",
          "TaskItemId",
          "UserId",
          "AssignedByUserId",
          "AssignedAt"
        ],
        "type": "string"
      },
      "TaskAssignmentSortingFieldsSortOption": {
        "type": "object",
        "properties": {
          "field": {
            "$ref": "#/components/schemas/TaskAssignmentSortingFields"
          },
          "direction": {
            "$ref": "#/components/schemas/SortDirection"
          }
        },
        "additionalProperties": false
      },
      "TaskCreateDto": {
        "type": "object",
        "properties": {
          "title": {
            "type": "string",
            "nullable": true
          },
          "description": {
            "type": "string",
            "nullable": true
          },
          "priority": {
            "$ref": "#/components/schemas/TaskPriority"
          },
          "dueDate": {
            "type": "string",
            "format": "date-time",
            "nullable": true
          },
          "projectId": {
            "type": "integer",
            "format": "int64"
          }
        },
        "additionalProperties": false
      },
      "TaskItemStatus": {
        "enum": [
          "Todo",
          "InProgress",
          "InReview",
          "Done",
          "Cancelled"
        ],
        "type": "string"
      },
      "TaskPriority": {
        "enum": [
          "Low",
          "Medium",
          "High",
          "Critical"
        ],
        "type": "string"
      },
      "TaskSortingFields": {
        "enum": [
          "Id",
          "Title",
          "Description",
          "Status",
          "Priority",
          "DueDate",
          "CompletedAt",
          "ProjectId",
          "CreatedByUserId",
          "CreatedAt",
          "UpdatedAt"
        ],
        "type": "string"
      },
      "TaskSortingFieldsSortOption": {
        "type": "object",
        "properties": {
          "field": {
            "$ref": "#/components/schemas/TaskSortingFields"
          },
          "direction": {
            "$ref": "#/components/schemas/SortDirection"
          }
        },
        "additionalProperties": false
      },
      "TaskStatus": {
        "enum": [
          "Created",
          "WaitingForActivation",
          "WaitingToRun",
          "Running",
          "WaitingForChildrenToComplete",
          "RanToCompletion",
          "Canceled",
          "Faulted"
        ],
        "type": "string"
      },
      "TaskStatusHistorySortingFields": {
        "enum": [
          "Id",
          "TaskItemId",
          "OldStatus",
          "NewStatus",
          "ChangedByUserId",
          "ChangedAt"
        ],
        "type": "string"
      },
      "TaskStatusHistorySortingFieldsSortOption": {
        "type": "object",
        "properties": {
          "field": {
            "$ref": "#/components/schemas/TaskStatusHistorySortingFields"
          },
          "direction": {
            "$ref": "#/components/schemas/SortDirection"
          }
        },
        "additionalProperties": false
      },
      "TaskUpdateDto": {
        "type": "object",
        "properties": {
          "title": {
            "type": "string",
            "nullable": true
          },
          "description": {
            "type": "string",
            "nullable": true
          },
          "dueDate": {
            "type": "string",
            "format": "date-time",
            "nullable": true
          },
          "projectId": {
            "type": "integer",
            "format": "int64"
          }
        },
        "additionalProperties": false
      },
      "TeamCreateDto": {
        "type": "object",
        "properties": {
          "name": {
            "type": "string",
            "nullable": true
          },
          "description": {
            "type": "string",
            "nullable": true
          }
        },
        "additionalProperties": false
      },
      "TeamSortingFields": {
        "enum": [
          "Id",
          "Name",
          "ManagerId",
          "CreatedAt"
        ],
        "type": "string"
      },
      "TeamSortingFieldsSortOption": {
        "type": "object",
        "properties": {
          "field": {
            "$ref": "#/components/schemas/TeamSortingFields"
          },
          "direction": {
            "$ref": "#/components/schemas/SortDirection"
          }
        },
        "additionalProperties": false
      },
      "TeamUpdateDto": {
        "type": "object",
        "properties": {
          "name": {
            "type": "string",
            "nullable": true
          },
          "description": {
            "type": "string",
            "nullable": true
          },
          "managerId": {
            "type": "string",
            "nullable": true
          }
        },
        "additionalProperties": false
      },
      "UserSortingFields": {
        "enum": [
          "Id",
          "UserName",
          "IsActive",
          "TeamId",
          "LastLoginAt",
          "CreatedAt"
        ],
        "type": "string"
      },
      "UserSortingFieldsSortOption": {
        "type": "object",
        "properties": {
          "field": {
            "$ref": "#/components/schemas/UserSortingFields"
          },
          "direction": {
            "$ref": "#/components/schemas/SortDirection"
          }
        },
        "additionalProperties": false
      },
      "UserStatusDto": {
        "type": "object",
        "properties": {
          "isActive": {
            "type": "boolean"
          }
        },
        "additionalProperties": false
      },
      "UserUpdateDto": {
        "type": "object",
        "properties": {
          "userName": {
            "type": "string",
            "nullable": true
          },
          "teamId": {
            "type": "integer",
            "format": "int64",
            "nullable": true
          },
          "shouldNotify": {
            "type": "boolean"
          },
          "notifyPeriod": {
            "type": "integer",
            "format": "int32"
          }
        },
        "additionalProperties": false
      }
    },
    "securitySchemes": {
      "Bearer": {
        "type": "apiKey",
        "description": "ضع الـ JWT هنا بدون كلمة Bearer",
        "name": "Authorization",
        "in": "header"
      }
    }
  },
  "security": [
    {
      "Bearer": [ ]
    }
  ]
}